Metadata-Version: 2.1
Name: ysr-monitor-v2
Version: 0.1.6
Summary: ysr_monitor
Home-page: https://github.com/ysrmonitor/ysr_monitor.git
Download-URL: https://github.com/ysrmonitor/ysr_monitor/archive/refs/tags/v0.1.6.tar.gz
Author: YSR
Author-email: ysr.monitor@gmail.com
License: MIT
Keywords: seed,monitoring,sensing,rpi
Platform: UNKNOWN
Classifier: Development Status :: 3 - Alpha
Classifier: Intended Audience :: Developers
Classifier: Topic :: Software Development :: Build Tools
Classifier: License :: OSI Approved :: MIT License
Classifier: Programming Language :: Python :: 3
Classifier: Programming Language :: Python :: 3.4
Classifier: Programming Language :: Python :: 3.5
Classifier: Programming Language :: Python :: 3.6
License-File: LICENSE.txt
